pytermcontrol/__init__.py
pytermcontrol/termcontrol.py
pytermcontrol-2022.9.19.dist-info/entry_points.txt
pytermcontrol-2022.9.19.dist-info/WHEEL
pytermcontrol-2022.9.19.dist-info/METADATA
pytermcontrol-2022.9.19.dist-info/RECORD
