Metadata-Version: 2.1
Name: pytermcontrol
Version: 2022.9.19
Summary: Python Terminal Control
Home-page: https://github.com/AXGKl/pytermcontrol
License: BSD
Author: Gunther Klessinger
Author-email: g_kle_ss_ing_er@gmx.de
Requires-Python: >=3.7,<4.0
Classifier: License :: Other/Proprietary License
Classifier: Programming Language :: Python :: 3
Classifier: Programming Language :: Python :: 3.10
Classifier: Programming Language :: Python :: 3.7
Classifier: Programming Language :: Python :: 3.8
Classifier: Programming Language :: Python :: 3.9
Project-URL: Repository, https://github.com/AXGKl/pytermcontrol
